tests/__init__.py
tests/conftest.py
tests/test_vectorizers.py
textvec/__init__.py
textvec/vectorizers.py
textvec-2.0.dist-info/LICENSE
textvec-2.0.dist-info/METADATA
textvec-2.0.dist-info/WHEEL
textvec-2.0.dist-info/top_level.txt
textvec-2.0.dist-info/RECORD
