Metadata-Version: 2.1
Name: textvec
Version: 2.0
Summary: Supervised text features extraction
Home-page: https://github.com/zveryansky/textvec
Author: Alex Zveryansky
Author-email: UNKNOWN
License: MIT
Keywords: text nlp vectorization scikit-learn
Platform: UNKNOWN
Classifier: License :: OSI Approved :: MIT License
Classifier: Programming Language :: Python :: 2.7
Classifier: Programming Language :: Python :: 3
Classifier: Programming Language :: Python :: 3.2
Classifier: Programming Language :: Python :: 3.3
Classifier: Programming Language :: Python :: 3.4
Classifier: Programming Language :: Python :: 3.5
Classifier: Programming Language :: Python :: 3.6
Classifier: Programming Language :: Python :: 3.7
Requires-Dist: scikit-learn
Requires-Dist: numpy
Requires-Dist: scipy
Requires-Dist: gensim
